{
	"$schema": "https://raw.githubusercontent.com/shiptest-ss13/Shiptest/master/_maps/ship_config_schema.json",
	"map_name": "Vaquero-class Light Frigate",
	"map_short_name": "Vaquero",
	"description": "'Vaquero' - это гибкая и дешевая военная модификация легкого коммерческого грузового судна, широко используемая InteQ Risk Management Group для пикетов, разведки и легкого сопровождения, а также для контрактов, которые не требуют более крупного и специализированного судна. В отличие от большинства суден InteQ, Vaquero оснащен базовым медицинским, инженерным и военным оборудованием, а его минимальные требования к экипажу отлично подходят для Vanguards с небольшим командованием и для учебных миссий. Как и аналогичные корабли, он оснащен большим грузовым отсеком, который может быть изменен по мере необходимости.",
	"map_path": "_maps/_mod_celadon/shuttles/inteq/inteq_vaquero.dmm",
	"enabled": true,
	"limit": 1,
	"prefix": "LIQSV",
	"faction": "/datum/faction/inteq",
	"tags": [
		"Generalist"
	],
	"namelists": [
		"BEASTS",
		"INTEQ"
	],
	"job_slots": {
		"Vanguard": {
			"outfit": "/datum/outfit/job/inteq/captain/celadon",
			"officer": true,
			"slots": 1
		},
		"Master At Arms": {
			"outfit": "/datum/outfit/job/inteq/warden/celadon",
			"officer": true,
			"slots": 1
		},
		"Artificer": {
			"outfit": "/datum/outfit/job/inteq/engineer/celadon",
			"slots": 1
		},
		"Corpsman": {
			"outfit": "/datum/outfit/job/inteq/paramedic/celadon",
			"slots": 1
		},
		"Enforcer": {
			"outfit": "/datum/outfit/job/inteq/security/celadon",
			"slots": 1
		},
		"Recruit": {
			"outfit": "/datum/outfit/job/inteq/assistant/celadon",
			"slots": 2
		}
	}
}
